[{"bonds":["a","b","c","d","e","f"],"cells":[{"id":"ede8009e-7f15-11ea-192a-a5c6135a9dcf","ok":false,"reasons":["extraction not ok","bond a is missing and has no usable possible_values (NotGiven)","bond a has unsupported value type Missing in v0","bond b is missing and has no usable possible_values (NotGiven)","bond b has unsupported value type Missing in v0","bond c is missing and has no usable possible_values (NotGiven)","bond c has unsupported value type Missing in v0","bond d is missing and has no usable possible_values (NotGiven)","bond d has unsupported value type Missing in v0","bond e is missing and has no usable possible_values (NotGiven)","bond e has unsupported value type Missing in v0","bond f is missing and has no usable possible_values (NotGiven)","bond f has unsupported value type Missing in v0"]}],"judgement":"fallback","oracle_samples":0,"oracle_skipped":null,"reasons":["extraction not ok","bond a is missing and has no usable possible_values (NotGiven)","bond a has unsupported value type Missing in v0","bond b is missing and has no usable possible_values (NotGiven)","bond b has unsupported value type Missing in v0","bond c is missing and has no usable possible_values (NotGiven)","bond c has unsupported value type Missing in v0","bond d is missing and has no usable possible_values (NotGiven)","bond d has unsupported value type Missing in v0","bond e is missing and has no usable possible_values (NotGiven)","bond e has unsupported value type Missing in v0","bond f is missing and has no usable possible_values (NotGiven)","bond f has unsupported value type Missing in v0"]},{"bonds":["counter"],"cells":[{"id":"5bd8b261-a89d-46a3-bb59-c95a1801c881","ok":false,"reasons":["extraction not ok","bond counter is missing and has no usable possible_values (NotGiven)","bond counter has unsupported value type Missing in v0"]}],"judgement":"fallback","oracle_samples":0,"oracle_skipped":null,"reasons":["extraction not ok","bond counter is missing and has no usable possible_values (NotGiven)","bond counter has unsupported value type Missing in v0"]},{"bonds":["limited"],"cells":[{"id":"f39435d3-ed67-45f1-ae56-49cf5ec69d6e","ok":false,"reasons":["extraction not ok","bond limited is missing and has no usable possible_values (NotGiven)","bond limited has unsupported value type Missing in v0"]}],"judgement":"fallback","oracle_samples":0,"oracle_skipped":null,"reasons":["extraction not ok","bond limited is missing and has no usable possible_values (NotGiven)","bond limited has unsupported value type Missing in v0"]},{"bonds":["limited_counter"],"cells":[{"id":"901c2b84-14b8-4deb-89d6-705a4972582c","ok":false,"reasons":["extraction not ok","bond limited_counter is missing and has no usable possible_values (NotGiven)","bond limited_counter has unsupported value type Missing in v0"]}],"judgement":"fallback","oracle_samples":0,"oracle_skipped":null,"reasons":["extraction not ok","bond limited_counter is missing and has no usable possible_values (NotGiven)","bond limited_counter has unsupported value type Missing in v0"]},{"bonds":["x1","x2"],"cells":[{"id":"3297233b-9567-4d5e-8138-93ebe20fed48","ok":false,"reasons":["extraction not ok","bond x1 is missing and has no usable possible_values (NotGiven)","bond x1 has unsupported value type Missing in v0","bond x2 is missing and has no usable possible_values (NotGiven)","bond x2 has unsupported value type Missing in v0"]}],"judgement":"fallback","oracle_samples":0,"oracle_skipped":null,"reasons":["extraction not ok","bond x1 is missing and has no usable possible_values (NotGiven)","bond x1 has unsupported value type Missing in v0","bond x2 is missing and has no usable possible_values (NotGiven)","bond x2 has unsupported value type Missing in v0"]},{"bonds":["x"],"cells":[{"id":"1ebba747-47f8-4ecd-809d-359e6d803ddc","ok":false,"reasons":["extraction not ok","bond x is missing and has no usable possible_values (NotGiven)","bond x has unsupported value type Missing in v0"]},{"id":"cb1fd532-7eac-11ea-307c-ab16b1977819","ok":false,"reasons":["extraction not ok","bond x is missing and has no usable possible_values (NotGiven)","bond x has unsupported value type Missing in v0"]},{"id":"cb65a4ee-02e5-4779-8728-b994d8af645d","ok":false,"reasons":["extraction not ok","bond x is missing and has no usable possible_values (NotGiven)","bond x has unsupported value type Missing in v0"]}],"judgement":"fallback","oracle_samples":0,"oracle_skipped":null,"reasons":["extraction not ok","bond x is missing and has no usable possible_values (NotGiven)","bond x has unsupported value type Missing in v0"]}]